setup.cfg
setup.py
cloudtb/__init__.py
cloudtb/bokeh.py
cloudtb/builtin.py
cloudtb/collections.py
cloudtb/dbe.py
cloudtb/dictionary.py
cloudtb/os.py
cloudtb/pandas.py
cloudtb/platform.py
cloudtb/plot.py
cloudtb/pprint.py
cloudtb/re.py
cloudtb/sys.py
cloudtb.egg-info/PKG-INFO
cloudtb.egg-info/SOURCES.txt
cloudtb.egg-info/dependency_links.txt
cloudtb.egg-info/pbr.json
cloudtb.egg-info/requires.txt
cloudtb.egg-info/top_level.txt