Metadata-Version: 1.1
Name: cloudtb
Version: 0.2.2
Summary: Open source methods to solve common problems
Home-page: https://github.com/cloudformdesign/cloudtb
Author: Garrett Berg
Author-email: garrett@cloudformdesign.com
License: MIT
Platform: UNKNOWN
Classifier: Intended Audience :: Developers
Classifier: License :: OSI Approved :: MIT License
Classifier: Operating System :: OS Independent
Classifier: Programming Language :: Python :: 2.7
Classifier: Programming Language :: Python :: 3
Classifier: Programming Language :: Python :: 3.4
Classifier: Topic :: Scientific/Engineering
Classifier: Topic :: Scientific/Engineering :: Visualization
Classifier: Topic :: Text Processing :: General
Classifier: Topic :: Utilities
Classifier: Topic :: Software Development
Classifier: Topic :: Software Development :: Libraries :: Python Modules
